{"_":{"postman_id":"33bbdda5-69df-45a8-bfc6-b2a08f18a8bf","exporter_id":"14670440"},"item":[{"id":"f9c67a7b-f741-426b-90ac-96bb099e162e","name":"Musics","item":[{"id":"73775af9-d850-44b2-998a-6c356da9b71c","name":"Stories","item":[{"id":"0d3ee92d-83f4-46f1-8dcf-5ad36aaebfda","name":"Authentication","item":[{"id":"be62acc4-7fd4-4878-86b6-21dba0cf6a11","name":"Generate id token from firebase","request":{"url":{"protocol":"https","path":["identitytoolkit","v3","relyingparty","verifyPassword"],"host":["www","googleapis","com"],"query":[{"key":"key","value":"{{FIREBASE_API_KEY}}"}],"variable":[]},"method":"POST","body":{"mode":"raw","raw":"{\r\n    \"email\":\"sudmondal2002@gmail.com\",\r\n    \"password\":\"123456\",\r\n    \"returnSecureToken\":true\r\n}","options":{"raw":{"language":"json"}}}},"response":[],"event":[{"listen":"test","script":{"id":"2fefa1ea-ad55-47f6-8265-9ed037b05940","type":"text/javascript","exec":["pm.collectionVariables.set('ID_TOKEN', pm.response.json()[\"idToken\"])"]}}]},{"id":"94712dd9-bf2a-46e4-b7ea-d3566a9b14ef","name":"Get User From Firebase","request":{"url":{"path":["auth","firebaseuser"],"host":["{{HOST}}"],"query":[],"variable":[]},"header":[{"key":"X_ID_Token","value":"{{ID_TOKEN}}"},{"key":"X_FCM_Token","value":"123456789"},{"key":"X-API-Token","value":"{{API_TOKEN}}"}],"method":"GET"},"response":[],"event":[{"listen":"test","script":{"id":"5fca2cec-5e5e-4ecf-a082-d0bc05be6a64","type":"text/javascript","exec":["pm.collectionVariables.set(\"USER_TOKEN\", pm.response.headers.get('X-Auth-Token'))\r","\r","pm.test(\"Status check\", ()=>{\r","    pm.response.to.have.status(200)\r","})\r","pm.test(\"Body Check\", ()=>{\r","    pm.response.to.have.jsonBody(\"email\")\r","    pm.response.to.have.jsonBody(\"firebase_uid\")\r","})\r",""]}}]},{"id":"24d8af84-e862-46d2-82c8-22266e45426c","name":"Get User From Server","request":{"url":{"path":["auth","user"],"host":["{{HOST}}"],"query":[],"variable":[]},"header":[{"key":"X-User-Token","value":"{{USER_TOKEN}}"},{"key":"X-API-Token","value":"{{API_TOKEN}}"}],"method":"GET"},"response":[],"event":[{"listen":"test","script":{"id":"8d743973-4989-491f-a240-23de84d8d835","type":"text/javascript","exec":["\r","pm.test(\"Status check\", ()=>{\r","    pm.response.to.have.status(200)\r","})\r","pm.test(\"Body Check\", ()=>{\r","    pm.response.to.have.jsonBody(\"email\")\r","    pm.response.to.have.jsonBody(\"firebase_uid\")\r","})\r",""]}}]}],"event":[]},{"id":"739a37a8-7675-4971-9bc5-d1e8da0fc575","name":"Without token","request":{"url":{"path":["stories"],"host":["{{HOST}}"],"query":[],"variable":[]},"method":"GET"},"response":[{"_":{"postman_previewlanguage":"json"},"id":"2fc5e587-9ff6-4e51-aaa8-ecea34123de8","name":"Without token","originalRequest":{"url":{"path":["stories"],"host":["{{HOST}}"],"query":[],"variable":[]},"method":"GET"},"status":"Forbidden","code":403,"header":[{"key":"Server","value":"Cowboy"},{"key":"Connection","value":"keep-alive"},{"key":"X-Powered-By","value":"Express"},{"key":"Content-Type","value":"application/json; charset=utf-8"},{"key":"Content-Length","value":"44"},{"key":"Etag","value":"W/\"2c-/X49cS+kChNSYTwvwOUtvpeHcOo\""},{"key":"Date","value":"Thu, 26 May 2022 11:54:21 GMT"},{"key":"Via","value":"1.1 vegur"}],"body":"{\n    \"message\": \"Forbidden: API key is required\"\n}","cookie":[]}],"event":[{"listen":"test","script":{"id":"d3e0bd9c-a84e-4518-ad40-26d0120bf422","type":"text/javascript","exec":["\r","pm.test(\"Status check\", ()=>{\r","    pm.response.to.have.status(403)\r","})\r","\r",""]}}]},{"id":"ec784429-3013-4492-9923-ddc3b76e959d","name":"Only API Token","request":{"url":{"path":["stories"],"host":["{{HOST}}"],"query":[],"variable":[]},"header":[{"key":"X-API-Token","value":"{{API_TOKEN}}"}],"method":"GET"},"response":[{"_":{"postman_previewlanguage":"json"},"id":"6fc2d1fd-5750-4330-a7d4-5dfd24504f49","name":"Only API Token","originalRequest":{"url":{"path":["stories"],"host":["{{HOST}}"],"query":[],"variable":[]},"header":[{"key":"X-API-Token","value":"{{API_TOKEN}}"}],"method":"GET"},"status":"Unauthorized","code":401,"header":[{"key":"Server","value":"Cowboy"},{"key":"Connection","value":"keep-alive"},{"key":"X-Powered-By","value":"Express"},{"key":"Content-Type","value":"application/json; charset=utf-8"},{"key":"Content-Length","value":"50"},{"key":"Etag","value":"W/\"32-RJBFAhWpXdRXWliQLHIuXsrJKh8\""},{"key":"Date","value":"Thu, 26 May 2022 11:54:31 GMT"},{"key":"Via","value":"1.1 vegur"}],"body":"{\n    \"message\": \"Unauthorized: User token is required\"\n}","cookie":[]}],"event":[{"listen":"test","script":{"id":"8c3a7df1-2283-4792-981b-6acb00b78a6f","type":"text/javascript","exec":["\r","pm.test(\"Status check\", ()=>{\r","    pm.response.to.have.status(401)\r","})\r","\r",""]}}]},{"id":"1c4725ae-c38a-442d-bb71-4b4c8115a6eb","name":"Only User Token","request":{"url":{"path":["stories"],"host":["{{HOST}}"],"query":[],"variable":[]},"header":[{"key":"X-User-Token","value":"{{USER_TOKEN}}"}],"method":"GET"},"response":[{"_":{"postman_previewlanguage":"json"},"id":"7aa29b72-bbaa-476a-b515-da1add96d201","name":"Only User Token","originalRequest":{"url":{"path":["stories"],"host":["{{HOST}}"],"query":[],"variable":[]},"header":[{"key":"X-User-Token","value":"{{USER_TOKEN}}"}],"method":"GET"},"status":"Forbidden","code":403,"header":[{"key":"Server","value":"Cowboy"},{"key":"Connection","value":"keep-alive"},{"key":"X-Powered-By","value":"Express"},{"key":"Content-Type","value":"application/json; charset=utf-8"},{"key":"Content-Length","value":"44"},{"key":"Etag","value":"W/\"2c-/X49cS+kChNSYTwvwOUtvpeHcOo\""},{"key":"Date","value":"Thu, 26 May 2022 11:54:39 GMT"},{"key":"Via","value":"1.1 vegur"}],"body":"{\n    \"message\": \"Forbidden: API key is required\"\n}","cookie":[]}],"event":[{"listen":"test","script":{"id":"e8e6f85a-7b5c-4b1c-9a47-018f05262cb6","type":"text/javascript","exec":["\r","pm.test(\"Status check\", ()=>{\r","    pm.response.to.have.status(403)\r","})\r","\r",""]}}]},{"id":"072be410-a2b6-4322-b678-4d2779030876","name":"Correct API Token and User Token","request":{"url":{"path":["stories"],"host":["{{HOST}}"],"query":[],"variable":[]},"header":[{"key":"X-API-Token","value":"{{API_TOKEN}}"},{"key":"X-User-Token","value":"{{USER_TOKEN}}"}],"method":"GET"},"response":[{"_":{"postman_previewlanguage":"json"},"id":"04b0514e-8a97-407d-a59f-ed9c42c6e313","name":"Correct API Token and User Token","originalRequest":{"url":{"path":["stories"],"host":["{{HOST}}"],"query":[],"variable":[]},"header":[{"key":"X-API-Token","value":"{{API_TOKEN}}"},{"key":"X-User-Token","value":"{{USER_TOKEN}}"}],"method":"GET"},"status":"OK","code":200,"header":[{"key":"Server","value":"Cowboy"},{"key":"Connection","value":"keep-alive"},{"key":"X-Powered-By","value":"Express"},{"key":"Content-Type","value":"application/json; charset=utf-8"},{"key":"Content-Length","value":"1084"},{"key":"Etag","value":"W/\"43c-zCzqXSydu4jMXHlA2lKIUeHe+Gs\""},{"key":"Date","value":"Thu, 26 May 2022 11:54:47 GMT"},{"key":"Via","value":"1.1 vegur"}],"body":"{\n    \"page\": 1,\n    \"length\": 4,\n    \"data\": [\n        {\n            \"id\": 1,\n            \"title\": \"Irubathu Rubaai\",\n            \"artist\": \"Mahe Amma\",\n            \"artwork\": \"/artworks_tamil/irubathu_rubaai.jpg\",\n            \"url\": \"/stories_tamil/irubathu_rubaai.mp3\",\n            \"duration\": 2520,\n            \"category\": {\n                \"id\": 1,\n                \"name\": \"Nostalgia\"\n            },\n            \"tags\": [\n                {\n                    \"id\": 1,\n                    \"name\": \"Popular\"\n                },\n                {\n                    \"id\": 2,\n                    \"name\": \"New\"\n                }\n            ]\n        },\n        {\n            \"id\": 2,\n            \"title\": \"Nanbanudan Payanam\",\n            \"artist\": \"Harnitha\",\n            \"artwork\": \"/artworks_tamil/nanbanudan_payanam.jpg\",\n            \"url\": \"/stories_tamil/nanbanudan_payanam.mp3\",\n            \"duration\": 1260,\n            \"category\": {\n                \"id\": 1,\n                \"name\": \"Nostalgia\"\n            },\n            \"tags\": [\n                {\n                    \"id\": 1,\n                    \"name\": \"Popular\"\n                },\n                {\n                    \"id\": 3,\n                    \"name\": \"Classic\"\n                }\n            ]\n        },\n        {\n            \"id\": 3,\n            \"title\": \"Siruvanum Maramum\",\n            \"artist\": \"Mahe Amma\",\n            \"artwork\": \"/artworks_tamil/athiyamanum_aalamaramum.jpg\",\n            \"url\": \"/stories_tamil/athiyamanum_aalamaramum.mp3\",\n            \"duration\": 1620,\n            \"category\": {\n                \"id\": 2,\n                \"name\": \"Travel\"\n            },\n            \"tags\": [\n                {\n                    \"id\": 1,\n                    \"name\": \"Popular\"\n                }\n            ]\n        },\n        {\n            \"id\": 4,\n            \"title\": \"Mullavin Sathuryam\",\n            \"artist\": \"Harnitha\",\n            \"artwork\": \"/artworks_tamil/amaichargalai_nakkaladitha_mulla.png\",\n            \"url\": \"/stories_tamil/amaichargalai_nakaladitha_mulla.mp3\",\n            \"duration\": 1620,\n            \"category\": {\n                \"id\": 3,\n                \"name\": \"Folk Tale\"\n            },\n            \"tags\": [\n                {\n                    \"id\": 3,\n                    \"name\": \"Classic\"\n                }\n            ]\n        }\n    ]\n}","cookie":[]}],"event":[{"listen":"test","script":{"id":"e0b32577-fa00-4d61-8375-8a6125ffb8e4","type":"text/javascript","exec":["\r","pm.test(\"Status check\", ()=>{\r","    pm.response.to.have.status(200)\r","})\r","pm.test(\"Body Check\", ()=>{\r","    pm.response.to.have.jsonBody(\"stories\")\r","})\r",""]}}]},{"id":"9da6d254-8df9-44ab-a736-dddd0bd555e6","name":"Category","request":{"url":{"path":["stories"],"host":["{{HOST}}"],"query":[{"key":"category_ids","value":"1"}],"variable":[]},"header":[{"key":"X-API-Token","value":"{{API_TOKEN}}"},{"key":"X-User-Token","value":"{{USER_TOKEN}}"}],"method":"GET"},"response":[{"_":{"postman_previewlanguage":"json"},"id":"092c1751-63a1-44e7-99d9-9fa3d132edf3","name":"Category","originalRequest":{"url":{"path":["stories"],"host":["{{HOST}}"],"query":[{"key":"category_ids","value":"1"}],"variable":[]},"header":[{"key":"X-API-Token","value":"{{API_TOKEN}}"},{"key":"X-User-Token","value":"{{USER_TOKEN}}"}],"method":"GET"},"status":"OK","code":200,"header":[{"key":"Server","value":"Cowboy"},{"key":"Connection","value":"keep-alive"},{"key":"X-Powered-By","value":"Express"},{"key":"Content-Type","value":"application/json; charset=utf-8"},{"key":"Content-Length","value":"289"},{"key":"Etag","value":"W/\"121-9Lu3ftfE60GLu2T3A0WUf7Rt+qU\""},{"key":"Date","value":"Thu, 26 May 2022 11:54:54 GMT"},{"key":"Via","value":"1.1 vegur"}],"body":"{\n    \"page\": 1,\n    \"length\": 1,\n    \"data\": [\n        {\n            \"id\": 1,\n            \"title\": \"Irubathu Rubaai\",\n            \"artist\": \"Mahe Amma\",\n            \"artwork\": \"/artworks_tamil/irubathu_rubaai.jpg\",\n            \"url\": \"/stories_tamil/irubathu_rubaai.mp3\",\n            \"duration\": 2520,\n            \"category\": {\n                \"id\": 1,\n                \"name\": \"Nostalgia\"\n            },\n            \"tags\": [\n                {\n                    \"id\": 1,\n                    \"name\": \"Popular\"\n                },\n                {\n                    \"id\": 2,\n                    \"name\": \"New\"\n                }\n            ]\n        }\n    ]\n}","cookie":[]}],"event":[{"listen":"test","script":{"id":"478fbd28-a60c-4150-9f04-72d797af6cf7","type":"text/javascript","exec":["\r","pm.test(\"Status check\", ()=>{\r","    pm.response.to.have.status(200)\r","})\r","pm.test(\"Body Check\", ()=>{\r","    pm.response.to.have.jsonBody(\"stories\")\r","})\r",""]}}]},{"id":"af1b5348-c573-45a5-be78-3eb55d932309","name":"Tags","request":{"url":{"path":["stories"],"host":["{{HOST}}"],"query":[{"key":"tag_ids","value":"1,3"}],"variable":[]},"header":[{"key":"X-API-Token","value":"{{API_TOKEN}}"},{"key":"X-User-Token","value":"{{USER_TOKEN}}"}],"method":"GET"},"response":[{"_":{"postman_previewlanguage":"json"},"id":"80af0e2b-fff8-48cc-afe4-92017b8d36f3","name":"Tags","originalRequest":{"url":{"path":["stories"],"host":["{{HOST}}"],"query":[{"key":"tag_ids","value":"1,3"}],"variable":[]},"header":[{"key":"X-API-Token","value":"{{API_TOKEN}}"},{"key":"X-User-Token","value":"{{USER_TOKEN}}"}],"method":"GET"},"status":"OK","code":200,"header":[{"key":"Server","value":"Cowboy"},{"key":"Connection","value":"keep-alive"},{"key":"X-Powered-By","value":"Express"},{"key":"Content-Type","value":"application/json; charset=utf-8"},{"key":"Content-Length","value":"813"},{"key":"Etag","value":"W/\"32d-dQbJ3NAuKsUR2ZX4Zp4kYo04Smg\""},{"key":"Date","value":"Thu, 26 May 2022 11:55:00 GMT"},{"key":"Via","value":"1.1 vegur"}],"body":"{\n    \"page\": 1,\n    \"length\": 3,\n    \"data\": [\n        {\n            \"id\": 1,\n            \"title\": \"Irubathu Rubaai\",\n            \"artist\": \"Mahe Amma\",\n            \"artwork\": \"/artworks_tamil/irubathu_rubaai.jpg\",\n            \"url\": \"/stories_tamil/irubathu_rubaai.mp3\",\n            \"duration\": 2520,\n            \"category\": {\n                \"id\": 1,\n                \"name\": \"Nostalgia\"\n            },\n            \"tags\": [\n                {\n                    \"id\": 1,\n                    \"name\": \"Popular\"\n                },\n                {\n                    \"id\": 2,\n                    \"name\": \"New\"\n                }\n            ]\n        },\n        {\n            \"id\": 3,\n            \"title\": \"Siruvanum Maramum\",\n            \"artist\": \"Mahe Amma\",\n            \"artwork\": \"/artworks_tamil/athiyamanum_aalamaramum.jpg\",\n            \"url\": \"/stories_tamil/athiyamanum_aalamaramum.mp3\",\n            \"duration\": 1620,\n            \"category\": {\n                \"id\": 2,\n                \"name\": \"Travel\"\n            },\n            \"tags\": [\n                {\n                    \"id\": 1,\n                    \"name\": \"Popular\"\n                }\n            ]\n        },\n        {\n            \"id\": 4,\n            \"title\": \"Mullavin Sathuryam\",\n            \"artist\": \"Harnitha\",\n            \"artwork\": \"/artworks_tamil/amaichargalai_nakkaladitha_mulla.png\",\n            \"url\": \"/stories_tamil/amaichargalai_nakaladitha_mulla.mp3\",\n            \"duration\": 1620,\n            \"category\": {\n                \"id\": 3,\n                \"name\": \"Folk Tale\"\n            },\n            \"tags\": [\n                {\n                    \"id\": 3,\n                    \"name\": \"Classic\"\n                }\n            ]\n        }\n    ]\n}","cookie":[]}],"event":[{"listen":"test","script":{"id":"8aa22c4d-f36a-49dc-8530-3cf335ad219c","type":"text/javascript","exec":["\r","pm.test(\"Status check\", ()=>{\r","    pm.response.to.have.status(200)\r","})\r","pm.test(\"Body Check\", ()=>{\r","    pm.response.to.have.jsonBody(\"stories\")\r","})\r",""]}}]},{"id":"9fadbe97-8915-4c1d-8971-5fee5cf4ce31","name":"Tags and Category","request":{"url":{"path":["stories"],"host":["{{HOST}}"],"query":[{"key":"tag_ids","value":"3"},{"key":"category_ids","value":"1"}],"variable":[]},"header":[{"key":"X-API-Token","value":"{{API_TOKEN}}"},{"key":"X-User-Token","value":"{{USER_TOKEN}}"}],"method":"GET"},"response":[{"_":{"postman_previewlanguage":"json"},"id":"51dab769-057e-478a-8c6a-de12d66c2ff4","name":"Tags and Category","originalRequest":{"url":{"path":["stories"],"host":["{{HOST}}"],"query":[{"key":"tag_ids","value":"3"},{"key":"category_ids","value":"1"}],"variable":[]},"header":[{"key":"X-API-Token","value":"{{API_TOKEN}}"},{"key":"X-User-Token","value":"{{USER_TOKEN}}"}],"method":"GET"},"status":"OK","code":200,"header":[{"key":"Server","value":"Cowboy"},{"key":"Connection","value":"keep-alive"},{"key":"X-Powered-By","value":"Express"},{"key":"Content-Type","value":"application/json; charset=utf-8"},{"key":"Content-Length","value":"561"},{"key":"Etag","value":"W/\"231-Jt4UKCgttFogkdET2Jx10we0+B4\""},{"key":"Date","value":"Thu, 26 May 2022 11:55:07 GMT"},{"key":"Via","value":"1.1 vegur"}],"body":"{\n    \"page\": 1,\n    \"length\": 2,\n    \"data\": [\n        {\n            \"id\": 1,\n            \"title\": \"Irubathu Rubaai\",\n            \"artist\": \"Mahe Amma\",\n            \"artwork\": \"/artworks_tamil/irubathu_rubaai.jpg\",\n            \"url\": \"/stories_tamil/irubathu_rubaai.mp3\",\n            \"duration\": 2520,\n            \"category\": {\n                \"id\": 1,\n                \"name\": \"Nostalgia\"\n            },\n            \"tags\": [\n                {\n                    \"id\": 1,\n                    \"name\": \"Popular\"\n                },\n                {\n                    \"id\": 2,\n                    \"name\": \"New\"\n                }\n            ]\n        },\n        {\n            \"id\": 4,\n            \"title\": \"Mullavin Sathuryam\",\n            \"artist\": \"Harnitha\",\n            \"artwork\": \"/artworks_tamil/amaichargalai_nakkaladitha_mulla.png\",\n            \"url\": \"/stories_tamil/amaichargalai_nakaladitha_mulla.mp3\",\n            \"duration\": 1620,\n            \"category\": {\n                \"id\": 3,\n                \"name\": \"Folk Tale\"\n            },\n            \"tags\": [\n                {\n                    \"id\": 3,\n                    \"name\": \"Classic\"\n                }\n            ]\n        }\n    ]\n}","cookie":[]}],"event":[{"listen":"test","script":{"id":"26d607e8-0c02-4a92-a663-509474a18252","type":"text/javascript","exec":["\r","pm.test(\"Status check\", ()=>{\r","    pm.response.to.have.status(200)\r","})\r","pm.test(\"Body Check\", ()=>{\r","    pm.response.to.have.jsonBody(\"stories\")\r","})\r",""]}}]},{"id":"479e3b0f-994f-412b-8ed1-a9b01dcce120","name":"Custom Pagination","request":{"url":{"path":["stories"],"host":["{{HOST}}"],"query":[{"key":"page","value":"2"},{"key":"limit","value":"2"}],"variable":[]},"header":[{"key":"X-API-Token","value":"{{API_TOKEN}}"},{"key":"X-User-Token","value":"{{USER_TOKEN}}"}],"method":"GET"},"response":[{"_":{"postman_previewlanguage":"json"},"id":"ce84c0b4-d6df-4e89-b7c3-c905ba624dad","name":"Custom Pagination","originalRequest":{"url":{"path":["stories"],"host":["{{HOST}}"],"query":[{"key":"page","value":"2"},{"key":"limit","value":"2"}],"variable":[]},"header":[{"key":"X-API-Token","value":"{{API_TOKEN}}"},{"key":"X-User-Token","value":"{{USER_TOKEN}}"}],"method":"GET"},"status":"OK","code":200,"header":[{"key":"Server","value":"Cowboy"},{"key":"Connection","value":"keep-alive"},{"key":"X-Powered-By","value":"Express"},{"key":"Content-Type","value":"application/json; charset=utf-8"},{"key":"Content-Length","value":"554"},{"key":"Etag","value":"W/\"22a-BXZXCl+fZUspRCW5dsfcp88dD6M\""},{"key":"Date","value":"Thu, 26 May 2022 11:55:15 GMT"},{"key":"Via","value":"1.1 vegur"}],"body":"{\n    \"page\": 2,\n    \"length\": 2,\n    \"data\": [\n        {\n            \"id\": 3,\n            \"title\": \"Siruvanum Maramum\",\n            \"artist\": \"Mahe Amma\",\n            \"artwork\": \"/artworks_tamil/athiyamanum_aalamaramum.jpg\",\n            \"url\": \"/stories_tamil/athiyamanum_aalamaramum.mp3\",\n            \"duration\": 1620,\n            \"category\": {\n                \"id\": 2,\n                \"name\": \"Travel\"\n            },\n            \"tags\": [\n                {\n                    \"id\": 1,\n                    \"name\": \"Popular\"\n                }\n            ]\n        },\n        {\n            \"id\": 4,\n            \"title\": \"Mullavin Sathuryam\",\n            \"artist\": \"Harnitha\",\n            \"artwork\": \"/artworks_tamil/amaichargalai_nakkaladitha_mulla.png\",\n            \"url\": \"/stories_tamil/amaichargalai_nakaladitha_mulla.mp3\",\n            \"duration\": 1620,\n            \"category\": {\n                \"id\": 3,\n                \"name\": \"Folk Tale\"\n            },\n            \"tags\": [\n                {\n                    \"id\": 3,\n                    \"name\": \"Classic\"\n                }\n            ]\n        }\n    ]\n}","cookie":[]}],"event":[{"listen":"test","script":{"id":"f313cfb3-b1e2-4767-b0be-e10301733c3a","type":"text/javascript","exec":["\r","pm.test(\"Status check\", ()=>{\r","    pm.response.to.have.status(200)\r","})\r","pm.test(\"Body Check\", ()=>{\r","    pm.response.to.have.jsonBody(\"stories\")\r","})\r",""]}}]},{"id":"9aedd728-245a-4edb-8c24-9c940de38d04","name":"From ID","request":{"url":{"path":["story","10"],"host":["{{HOST}}"],"query":[],"variable":[]},"header":[{"key":"X-API-Token","value":"{{API_TOKEN}}"},{"key":"X-User-Token","value":"{{USER_TOKEN}}"}],"method":"GET"},"response":[{"_":{"postman_previewlanguage":"json"},"id":"653793f5-a9e8-4365-8a0e-2e0761569f2d","name":"From ID","originalRequest":{"url":{"path":["story","2"],"host":["{{HOST}}"],"query":[],"variable":[]},"header":[{"key":"X-API-Token","value":"{{API_TOKEN}}"},{"key":"X-User-Token","value":"{{USER_TOKEN}}"}],"method":"GET"},"status":"OK","code":200,"header":[{"key":"Server","value":"Cowboy"},{"key":"Connection","value":"keep-alive"},{"key":"X-Powered-By","value":"Express"},{"key":"Content-Type","value":"application/json; charset=utf-8"},{"key":"Content-Length","value":"357"},{"key":"Etag","value":"W/\"165-LrhmKpMdambItK1tIJk0gUG11mU\""},{"key":"Date","value":"Thu, 26 May 2022 11:55:29 GMT"},{"key":"Via","value":"1.1 vegur"}],"body":"{\n    \"data\": {\n        \"id\": 2,\n        \"title\": \"Nanbanudan Payanam\",\n        \"artist\": \"Harnitha\",\n        \"artwork\": \"/artworks_tamil/nanbanudan_payanam.jpg\",\n        \"url\": \"/stories_tamil/nanbanudan_payanam.mp3\",\n        \"duration\": 1260,\n        \"category\": {\n            \"id\": 1,\n            \"name\": \"Nostalgia\"\n        },\n        \"tags\": [\n            {\n                \"id\": 1,\n                \"name\": \"Popular\",\n                \"story_tags\": {\n                    \"story_id\": 2,\n                    \"tag_id\": 1\n                }\n            },\n            {\n                \"id\": 3,\n                \"name\": \"Classic\",\n                \"story_tags\": {\n                    \"story_id\": 2,\n                    \"tag_id\": 3\n                }\n            }\n        ]\n    }\n}","cookie":[]}],"event":[{"listen":"test","script":{"id":"255e7dfd-a9ef-4139-862d-c4395cf754e7","type":"text/javascript","exec":["\r","pm.test(\"Status check\", ()=>{\r","    pm.response.to.have.status(200)\r","})\r","pm.test(\"Body Check\", ()=>{\r","    pm.response.to.have.jsonBody(\"story\")\r","})\r",""]}}]}],"event":[]},{"id":"e9b8e21b-ad7a-4e0e-8511-64d82330d4c9","name":"Filters","item":[{"id":"45547ff6-e43f-4f0b-bd6a-44c3d73e49de","name":"Categories","request":{"url":{"path":["categories"],"host":["{{HOST}}"],"query":[],"variable":[]},"header":[{"key":"X-API-Token","value":"{{API_TOKEN}}"},{"key":"X-User-Token","value":"{{USER_TOKEN}}"}],"method":"GET"},"response":[{"_":{"postman_previewlanguage":"json"},"id":"f7c378f8-38d1-4d51-8b29-f8016a71ae9b","name":"Categories","originalRequest":{"url":{"path":["categories"],"host":["{{HOST}}"],"query":[],"variable":[]},"header":[{"key":"X-API-Token","value":"{{API_TOKEN}}"},{"key":"X-User-Token","value":"{{USER_TOKEN}}"}],"method":"GET"},"status":"OK","code":200,"header":[{"key":"Server","value":"Cowboy"},{"key":"Connection","value":"keep-alive"},{"key":"X-Powered-By","value":"Express"},{"key":"Content-Type","value":"application/json; charset=utf-8"},{"key":"Content-Length","value":"134"},{"key":"Etag","value":"W/\"86-6A40tXK24KTf8F8ASeiTIN8nL0o\""},{"key":"Date","value":"Thu, 26 May 2022 11:55:37 GMT"},{"key":"Via","value":"1.1 vegur"}],"body":"[\n    {\n        \"id\": 1,\n        \"name\": \"Nostalgia\"\n    },\n    {\n        \"id\": 2,\n        \"name\": \"Travel\"\n    },\n    {\n        \"id\": 3,\n        \"name\": \"Folk Tale\"\n    },\n    {\n        \"id\": 4,\n        \"name\": \"Fiction\"\n    },\n    {\n        \"id\": 5,\n        \"name\": \"Fantasy\"\n    }\n]","cookie":[]}],"event":[{"listen":"test","script":{"id":"a3b0fd87-7c60-4456-930a-f6bb1978b240","type":"text/javascript","exec":["\r","pm.test(\"Status check\", ()=>{\r","    pm.response.to.have.status(200)\r","})\r","pm.test(\"Body Check\", ()=>{\r","    pm.response.to.have.body()\r","})\r",""]}}]},{"id":"4681de5a-e7f9-4e56-a444-d5e617729d9e","name":"Tags","request":{"url":{"path":["tags"],"host":["{{HOST}}"],"query":[],"variable":[]},"header":[{"key":"X-API-Token","value":"{{API_TOKEN}}"},{"key":"X-User-Token","value":"{{USER_TOKEN}}"}],"method":"GET"},"response":[{"_":{"postman_previewlanguage":"json"},"id":"218478fc-f1a1-4405-bd17-7ae19a03248c","name":"Tags","originalRequest":{"url":{"path":["tags"],"host":["{{HOST}}"],"query":[],"variable":[]},"header":[{"key":"X-API-Token","value":"{{API_TOKEN}}"},{"key":"X-User-Token","value":"{{USER_TOKEN}}"}],"method":"GET"},"status":"OK","code":200,"header":[{"key":"Server","value":"Cowboy"},{"key":"Connection","value":"keep-alive"},{"key":"X-Powered-By","value":"Express"},{"key":"Content-Type","value":"application/json; charset=utf-8"},{"key":"Content-Length","value":"75"},{"key":"Etag","value":"W/\"4b-ofgJGicP0McTI2yOgTdcWVVfDpU\""},{"key":"Date","value":"Thu, 26 May 2022 11:55:45 GMT"},{"key":"Via","value":"1.1 vegur"}],"body":"[\n    {\n        \"id\": 1,\n        \"name\": \"Popular\"\n    },\n    {\n        \"id\": 2,\n        \"name\": \"New\"\n    },\n    {\n        \"id\": 3,\n        \"name\": \"Classic\"\n    }\n]","cookie":[]}],"event":[{"listen":"test","script":{"id":"be9e5e75-782d-4d26-add2-92a5be5701a1","type":"text/javascript","exec":["\r","pm.test(\"Status check\", ()=>{\r","    pm.response.to.have.status(200)\r","})\r","pm.test(\"Body Check\", ()=>{\r","    pm.response.to.have.body()\r","})\r",""]}}]}],"event":[]},{"id":"b4c848f4-f5f9-42a5-9753-57d3ee9db245","name":"Get Musics","request":{"url":{"path":["musics"],"host":["{{HOST}}"],"query":[],"variable":[]},"header":[{"key":"X-API-Token","value":"{{API_TOKEN}}"},{"key":"X-User-Token","value":"{{USER_TOKEN}}"}],"method":"GET"},"response":[{"_":{"postman_previewlanguage":"json"},"id":"3f86a396-c594-486f-9657-a14e67f5ed06","name":"Correct API Token and User Token","originalRequest":{"url":{"path":["musics"],"host":["{{HOST}}"],"query":[],"variable":[]},"header":[{"key":"X-API-Token","value":"{{API_TOKEN}}"},{"key":"X-User-Token","value":"{{USER_TOKEN}}"}],"method":"GET"},"status":"OK","code":200,"header":[{"key":"X-Powered-By","value":"Express"},{"key":"X-Total-Count","value":"2"},{"key":"X-Page-Count","value":"2"},{"key":"X-Page-Limit","value":"10"},{"key":"X-Page-No","value":"1"},{"key":"Content-Type","value":"application/json; charset=utf-8"},{"key":"Content-Length","value":"553"},{"key":"ETag","value":"W/\"229-9FYqj7MuovsUEQlLVPRJW04YOh8\""},{"key":"Date","value":"Thu, 09 Jun 2022 17:38:02 GMT"},{"key":"Connection","value":"keep-alive"},{"key":"Keep-Alive","value":"timeout=5"}],"body":"{\n    \"musics\": [\n        {\n            \"id\": 3,\n            \"title\": \"Siruvanum Maramum\",\n            \"artist\": \"Mahe Amma\",\n            \"artwork\": \"/artworks_tamil/athiyamanum_aalamaramum.jpg\",\n            \"url\": \"/stories_tamil/athiyamanum_aalamaramum.mp3\",\n            \"duration\": 1620,\n            \"audio_type\": \"music\",\n            \"category\": {\n                \"id\": 2,\n                \"name\": \"Travel\"\n            },\n            \"tags\": [\n                {\n                    \"id\": 3,\n                    \"name\": \"Classic\"\n                }\n            ]\n        },\n        {\n            \"id\": 4,\n            \"title\": \"Mullavin Sathuryam\",\n            \"artist\": \"Harnitha\",\n            \"artwork\": \"/artworks_tamil/amaichargalai_nakkaladitha_mulla.png\",\n            \"url\": \"/stories_tamil/amaichargalai_nakaladitha_mulla.mp3\",\n            \"duration\": 1620,\n            \"audio_type\": \"music\",\n            \"category\": {\n                \"id\": 3,\n                \"name\": \"Folk Tale\"\n            },\n            \"tags\": []\n        }\n    ]\n}","cookie":[]}],"event":[{"listen":"test","script":{"id":"13c16d09-de0d-4f02-8828-6b6691a89707","type":"text/javascript","exec":["\r","pm.test(\"Status check\", ()=>{\r","    pm.response.to.have.status(200)\r","})\r","pm.test(\"Body Check\", ()=>{\r","    pm.response.to.have.jsonBody(\"musics\")\r","})\r",""]}}]},{"id":"f4248426-d1eb-498b-b63f-020b40bb186a","name":"Category","request":{"url":{"path":["musics"],"host":["{{HOST}}"],"query":[{"key":"category_ids","value":"2"}],"variable":[]},"header":[{"key":"X-API-Token","value":"{{API_TOKEN}}"},{"key":"X-User-Token","value":"{{USER_TOKEN}}"}],"method":"GET"},"response":[{"_":{"postman_previewlanguage":"json"},"id":"83c6c894-073c-4ab0-b248-39c0df38417d","name":"Category","originalRequest":{"url":{"path":["musics"],"host":["{{HOST}}"],"query":[{"key":"category_ids","value":"2"}],"variable":[]},"header":[{"key":"X-API-Token","value":"{{API_TOKEN}}"},{"key":"X-User-Token","value":"{{USER_TOKEN}}"}],"method":"GET"},"status":"OK","code":200,"header":[{"key":"X-Powered-By","value":"Express"},{"key":"X-Total-Count","value":"1"},{"key":"X-Page-Count","value":"1"},{"key":"X-Page-Limit","value":"10"},{"key":"X-Page-No","value":"1"},{"key":"Content-Type","value":"application/json; charset=utf-8"},{"key":"Content-Length","value":"285"},{"key":"ETag","value":"W/\"11d-iw3gy77WSf+C9C1erFusDrQ8ZjM\""},{"key":"Date","value":"Thu, 09 Jun 2022 17:38:22 GMT"},{"key":"Connection","value":"keep-alive"},{"key":"Keep-Alive","value":"timeout=5"}],"body":"{\n    \"musics\": [\n        {\n            \"id\": 3,\n            \"title\": \"Siruvanum Maramum\",\n            \"artist\": \"Mahe Amma\",\n            \"artwork\": \"/artworks_tamil/athiyamanum_aalamaramum.jpg\",\n            \"url\": \"/stories_tamil/athiyamanum_aalamaramum.mp3\",\n            \"duration\": 1620,\n            \"audio_type\": \"music\",\n            \"category\": {\n                \"id\": 2,\n                \"name\": \"Travel\"\n            },\n            \"tags\": [\n                {\n                    \"id\": 3,\n                    \"name\": \"Classic\"\n                }\n            ]\n        }\n    ]\n}","cookie":[]}],"event":[{"listen":"test","script":{"id":"680df2e7-ab2c-45bd-8ada-24326770260e","type":"text/javascript","exec":["\r","pm.test(\"Status check\", ()=>{\r","    pm.response.to.have.status(200)\r","})\r","pm.test(\"Body Check\", ()=>{\r","    pm.response.to.have.jsonBody(\"musics\")\r","})\r",""]}}]},{"id":"e86ca9ce-d2ff-4223-b9b1-a643f60545b6","name":"Tags","request":{"url":{"path":["musics"],"host":["{{HOST}}"],"query":[{"key":"tag_ids","value":"1,3"}],"variable":[]},"header":[{"key":"X-API-Token","value":"{{API_TOKEN}}"},{"key":"X-User-Token","value":"{{USER_TOKEN}}"}],"method":"GET"},"response":[{"_":{"postman_previewlanguage":"json"},"id":"6da36c6f-a3d5-4a1b-9339-d1ecea79cd82","name":"Tags","originalRequest":{"url":{"path":["musics"],"host":["{{HOST}}"],"query":[{"key":"tag_ids","value":"1,3"}],"variable":[]},"header":[{"key":"X-API-Token","value":"{{API_TOKEN}}"},{"key":"X-User-Token","value":"{{USER_TOKEN}}"}],"method":"GET"},"status":"OK","code":200,"header":[{"key":"X-Powered-By","value":"Express"},{"key":"X-Total-Count","value":"1"},{"key":"X-Page-Count","value":"1"},{"key":"X-Page-Limit","value":"10"},{"key":"X-Page-No","value":"1"},{"key":"Content-Type","value":"application/json; charset=utf-8"},{"key":"Content-Length","value":"285"},{"key":"ETag","value":"W/\"11d-iw3gy77WSf+C9C1erFusDrQ8ZjM\""},{"key":"Date","value":"Thu, 09 Jun 2022 17:38:31 GMT"},{"key":"Connection","value":"keep-alive"},{"key":"Keep-Alive","value":"timeout=5"}],"body":"{\n    \"musics\": [\n        {\n            \"id\": 3,\n            \"title\": \"Siruvanum Maramum\",\n            \"artist\": \"Mahe Amma\",\n            \"artwork\": \"/artworks_tamil/athiyamanum_aalamaramum.jpg\",\n            \"url\": \"/stories_tamil/athiyamanum_aalamaramum.mp3\",\n            \"duration\": 1620,\n            \"audio_type\": \"music\",\n            \"category\": {\n                \"id\": 2,\n                \"name\": \"Travel\"\n            },\n            \"tags\": [\n                {\n                    \"id\": 3,\n                    \"name\": \"Classic\"\n                }\n            ]\n        }\n    ]\n}","cookie":[]}],"event":[{"listen":"test","script":{"id":"2373ea15-1319-4aa7-b02d-81a679dafb56","type":"text/javascript","exec":["\r","pm.test(\"Status check\", ()=>{\r","    pm.response.to.have.status(200)\r","})\r","pm.test(\"Body Check\", ()=>{\r","    pm.response.to.have.jsonBody(\"musics\")\r","})\r",""]}}]},{"id":"74db3670-72aa-4c0b-9927-db3ec54f163c","name":"Tags and Category","request":{"url":{"path":["musics"],"host":["{{HOST}}"],"query":[{"key":"tag_ids","value":"3"},{"key":"category_ids","value":"1"}],"variable":[]},"header":[{"key":"X-API-Token","value":"{{API_TOKEN}}"},{"key":"X-User-Token","value":"{{USER_TOKEN}}"}],"method":"GET"},"response":[{"_":{"postman_previewlanguage":"json"},"id":"ef4183bb-3b0e-4c5b-a02c-76e1cee3133b","name":"Tags and Category","originalRequest":{"url":{"path":["musics"],"host":["{{HOST}}"],"query":[{"key":"tag_ids","value":"3"},{"key":"category_ids","value":"1"}],"variable":[]},"header":[{"key":"X-API-Token","value":"{{API_TOKEN}}"},{"key":"X-User-Token","value":"{{USER_TOKEN}}"}],"method":"GET"},"status":"OK","code":200,"header":[{"key":"X-Powered-By","value":"Express"},{"key":"X-Total-Count","value":"1"},{"key":"X-Page-Count","value":"1"},{"key":"X-Page-Limit","value":"10"},{"key":"X-Page-No","value":"1"},{"key":"Content-Type","value":"application/json; charset=utf-8"},{"key":"Content-Length","value":"285"},{"key":"ETag","value":"W/\"11d-iw3gy77WSf+C9C1erFusDrQ8ZjM\""},{"key":"Date","value":"Thu, 09 Jun 2022 17:38:38 GMT"},{"key":"Connection","value":"keep-alive"},{"key":"Keep-Alive","value":"timeout=5"}],"body":"{\n    \"musics\": [\n        {\n            \"id\": 3,\n            \"title\": \"Siruvanum Maramum\",\n            \"artist\": \"Mahe Amma\",\n            \"artwork\": \"/artworks_tamil/athiyamanum_aalamaramum.jpg\",\n            \"url\": \"/stories_tamil/athiyamanum_aalamaramum.mp3\",\n            \"duration\": 1620,\n            \"audio_type\": \"music\",\n            \"category\": {\n                \"id\": 2,\n                \"name\": \"Travel\"\n            },\n            \"tags\": [\n                {\n                    \"id\": 3,\n                    \"name\": \"Classic\"\n                }\n            ]\n        }\n    ]\n}","cookie":[]}],"event":[{"listen":"test","script":{"id":"5522d978-e5a8-4734-805b-73a01c3354d1","type":"text/javascript","exec":["\r","pm.test(\"Status check\", ()=>{\r","    pm.response.to.have.status(200)\r","})\r","pm.test(\"Body Check\", ()=>{\r","    pm.response.to.have.jsonBody(\"musics\")\r","})\r",""]}}]},{"id":"f80e7a59-10e8-424a-8060-2cedaadfe0ac","name":"Custom Pagination","request":{"url":{"path":["musics"],"host":["{{HOST}}"],"query":[{"key":"page","value":"1"},{"key":"limit","value":"2"}],"variable":[]},"header":[{"key":"X-API-Token","value":"{{API_TOKEN}}"},{"key":"X-User-Token","value":"{{USER_TOKEN}}"}],"method":"GET"},"response":[{"_":{"postman_previewlanguage":"json"},"id":"30cb969c-3d5c-4316-9922-5e5aef6c7d1f","name":"Custom Pagination","originalRequest":{"url":{"path":["musics"],"host":["{{HOST}}"],"query":[{"key":"page","value":"1"},{"key":"limit","value":"2"}],"variable":[]},"header":[{"key":"X-API-Token","value":"{{API_TOKEN}}"},{"key":"X-User-Token","value":"{{USER_TOKEN}}"}],"method":"GET"},"status":"OK","code":200,"header":[{"key":"X-Powered-By","value":"Express"},{"key":"X-Total-Count","value":"2"},{"key":"X-Page-Count","value":"2"},{"key":"X-Page-Limit","value":"2"},{"key":"X-Page-No","value":"1"},{"key":"Content-Type","value":"application/json; charset=utf-8"},{"key":"Content-Length","value":"553"},{"key":"ETag","value":"W/\"229-9FYqj7MuovsUEQlLVPRJW04YOh8\""},{"key":"Date","value":"Thu, 09 Jun 2022 17:38:59 GMT"},{"key":"Connection","value":"keep-alive"},{"key":"Keep-Alive","value":"timeout=5"}],"body":"{\n    \"musics\": [\n        {\n            \"id\": 3,\n            \"title\": \"Siruvanum Maramum\",\n            \"artist\": \"Mahe Amma\",\n            \"artwork\": \"/artworks_tamil/athiyamanum_aalamaramum.jpg\",\n            \"url\": \"/stories_tamil/athiyamanum_aalamaramum.mp3\",\n            \"duration\": 1620,\n            \"audio_type\": \"music\",\n            \"category\": {\n                \"id\": 2,\n                \"name\": \"Travel\"\n            },\n            \"tags\": [\n                {\n                    \"id\": 3,\n                    \"name\": \"Classic\"\n                }\n            ]\n        },\n        {\n            \"id\": 4,\n            \"title\": \"Mullavin Sathuryam\",\n            \"artist\": \"Harnitha\",\n            \"artwork\": \"/artworks_tamil/amaichargalai_nakkaladitha_mulla.png\",\n            \"url\": \"/stories_tamil/amaichargalai_nakaladitha_mulla.mp3\",\n            \"duration\": 1620,\n            \"audio_type\": \"music\",\n            \"category\": {\n                \"id\": 3,\n                \"name\": \"Folk Tale\"\n            },\n            \"tags\": []\n        }\n    ]\n}","cookie":[]}],"event":[{"listen":"test","script":{"id":"e3c26ff7-1196-4cb6-a64e-57bf1f55a029","type":"text/javascript","exec":["\r","pm.test(\"Status check\", ()=>{\r","    pm.response.to.have.status(200)\r","})\r","pm.test(\"Body Check\", ()=>{\r","    pm.response.to.have.jsonBody(\"musics\")\r","})\r",""]}}]},{"id":"df597a7f-1b70-4b97-b10f-2ba8ced3175b","name":"From ID","request":{"url":{"path":["music","3"],"host":["{{HOST}}"],"query":[],"variable":[]},"header":[{"key":"X-API-Token","value":"{{API_TOKEN}}"},{"key":"X-User-Token","value":"{{USER_TOKEN}}"}],"method":"GET"},"response":[{"_":{"postman_previewlanguage":"json"},"id":"45353e4f-9aa3-4fc1-99bc-b492d06dcef7","name":"From ID","originalRequest":{"url":{"path":["music","3"],"host":["{{HOST}}"],"query":[],"variable":[]},"header":[{"key":"X-API-Token","value":"{{API_TOKEN}}"},{"key":"X-User-Token","value":"{{USER_TOKEN}}"}],"method":"GET"},"status":"OK","code":200,"header":[{"key":"X-Powered-By","value":"Express"},{"key":"Content-Type","value":"application/json; charset=utf-8"},{"key":"Content-Length","value":"261"},{"key":"ETag","value":"W/\"105-lw/Y5KXavRdpOZBhTJUDPxmrBEA\""},{"key":"Date","value":"Thu, 09 Jun 2022 17:39:12 GMT"},{"key":"Connection","value":"keep-alive"},{"key":"Keep-Alive","value":"timeout=5"}],"body":"{\n    \"music\": {\n        \"id\": 3,\n        \"title\": \"Siruvanum Maramum\",\n        \"artist\": \"Mahe Amma\",\n        \"artwork\": \"/artworks_tamil/athiyamanum_aalamaramum.jpg\",\n        \"url\": \"/stories_tamil/athiyamanum_aalamaramum.mp3\",\n        \"duration\": 1620,\n        \"category\": {\n            \"id\": 2,\n            \"name\": \"Travel\"\n        },\n        \"tags\": [\n            {\n                \"id\": 3,\n                \"name\": \"Classic\"\n            }\n        ]\n    }\n}","cookie":[]}],"event":[{"listen":"test","script":{"id":"8b97b9fc-1027-4f64-a04c-750cf36b5352","type":"text/javascript","exec":["\r","pm.test(\"Status check\", ()=>{\r","    pm.response.to.have.status(200)\r","})\r","pm.test(\"Body Check\", ()=>{\r","    pm.response.to.have.jsonBody(\"music\")\r","})\r",""]}}]}],"event":[]},{"id":"f256595a-7a1d-482d-8b9c-a73abcf63d5d","name":"Meditation","item":[{"id":"3a3eefc0-a8af-4d2f-a7c6-c2e9b69a1e9d","name":"Get mediation","request":{"url":{"path":["meditations"],"host":["{{HOST}}"],"query":[],"variable":[]},"header":[{"key":"X-API-Token","value":"{{API_TOKEN}}"},{"key":"X-User-Token","value":"{{USER_TOKEN}}"}],"method":"GET"},"response":[],"event":[{"listen":"test","script":{"id":"b0433a47-d8f3-4964-a226-dc51d15f0776","type":"text/javascript","exec":["\r","pm.test(\"Status check\", ()=>{\r","    pm.response.to.have.status(200)\r","})\r","pm.test(\"Body Check\", ()=>{\r","    pm.response.to.have.body()\r","})\r",""]}}]},{"id":"ce230ec4-1eb1-44c2-aa5f-758c25f4423a","name":"Get mediation steps","request":{"url":{"path":["meditations","10","steps"],"host":["{{HOST}}"],"query":[],"variable":[]},"header":[{"key":"X-API-Token","value":"{{API_TOKEN}}"},{"key":"X-User-Token","value":"{{USER_TOKEN}}"}],"method":"GET"},"response":[],"event":[{"listen":"test","script":{"id":"f9d40de4-5714-4d74-9ddf-becc70b9fa56","type":"text/javascript","exec":["\r","pm.test(\"Status check\", ()=>{\r","    pm.response.to.have.status(200)\r","})\r","pm.test(\"Body Check\", ()=>{\r","    pm.response.to.have.jsonBody(\"meditation_steps\")\r","})\r",""]}}]},{"id":"5b3d46d7-e462-465e-bb6f-93917c0a05fc","name":"Tags","request":{"url":{"path":["meditations"],"host":["{{HOST}}"],"query":[{"key":"tag_ids","value":"12"}],"variable":[]},"header":[{"key":"X-API-Token","value":"{{API_TOKEN}}"},{"key":"X-User-Token","value":"{{USER_TOKEN}}"}],"method":"GET"},"response":[],"event":[{"listen":"test","script":{"id":"16d2aa31-d00f-4c3c-aa5a-f0363017a40d","type":"text/javascript","exec":["\r","pm.test(\"Status check\", ()=>{\r","    pm.response.to.have.status(200)\r","})\r","pm.test(\"Body Check\", ()=>{\r","    pm.response.to.have.body()\r","})\r",""]}}]},{"id":"5453fa19-fb6f-4cbc-98ae-0048574d9476","name":"Categories","request":{"url":{"path":["meditations"],"host":["{{HOST}}"],"query":[{"key":"category_ids","value":"10"}],"variable":[]},"header":[{"key":"X-API-Token","value":"{{API_TOKEN}}"},{"key":"X-User-Token","value":"{{USER_TOKEN}}"}],"method":"GET"},"response":[],"event":[{"listen":"test","script":{"id":"e358a328-28b1-40cd-81f0-709b06278a56","type":"text/javascript","exec":["\r","pm.test(\"Status check\", ()=>{\r","    pm.response.to.have.status(200)\r","})\r","pm.test(\"Body Check\", ()=>{\r","    pm.response.to.have.body()\r","})\r",""]}}]}],"event":[]},{"id":"56a895b2-0bd4-4ac4-a372-7420b0e2af65","name":"Orders","item":[{"id":"068f07cc-1d3f-4939-8be5-213e54314f17","name":"Create Order","request":{"url":{"path":["orders","create"],"host":["{{HOST}}"],"query":[],"variable":[]},"header":[{"key":"X-API-Token","value":"{{API_TOKEN}}"},{"key":"X-User-Token","value":"{{USER_TOKEN}}"}],"method":"POST","body":{"mode":"raw","raw":"{\r\n    \"content_id\":\"10\",\r\n    \"content_type\":\"audio\",\r\n    \"valid_till\":\"2023-01-01\",\r\n    \"amount\": 100,\r\n    \"currency\": \"INR\"\r\n}","options":{"raw":{"language":"json"}}}},"response":[],"event":[{"listen":"test","script":{"id":"8b975dbd-5fa6-4760-8892-21ee8b05fad4","type":"text/javascript","exec":["\r","pm.test(\"Status check\", ()=>{\r","    pm.response.to.have.status(201)\r","})\r","pm.test(\"Body Check\", ()=>{\r","    pm.response.to.have.jsonBody(\"order\")\r","})\r",""]}}]}],"event":[]}],"event":[{"listen":"prerequest","script":{"id":"85f94ae4-2766-4735-8003-3575a4a554d8","type":"text/javascript","exec":[""]}},{"listen":"test","script":{"id":"5c969b7c-a39c-4908-adfc-cd4126e90b02","type":"text/javascript","exec":[""]}},{"listen":"prerequest","script":{"id":"aff06f70-4fc7-42f0-a398-118e8fc20461","type":"text/javascript","exec":["pm.sendRequest(`http://localhost:3000/api/start-request?current_request=${pm.request.url.getPath()}`);"]}},{"listen":"test","script":{"id":"9a16fcf5-750d-4146-acc4-af20f9b48c51","type":"text/javascript","exec":["pm.sendRequest(`http://localhost:3000/api/end-request?current_request=${pm.request.url.getPath()}`);"]}}],"variable":[{"type":"string","value":"http://localhost:8000","key":"HOST"},{"type":"string","value":"bfbaff4b-05b6-499d-8e78-5b65c4d16296","key":"API_TOKEN"},{"type":"string","value":"AIzaSyBtMI-p7O9n5OJ1MxEO-UNoRdsejdN2TOI ","key":"FIREBASE_API_KEY"},{"type":"string","value":"eyJhbGciOiJSUzI1NiIsImtpZCI6IjFhZWY1NjlmNTI0MTRlOWY0YTcxMDRiNmQwNzFmMDY2ZGZlZWQ2NzciLCJ0eXAiOiJKV1QifQ.eyJpc3MiOiJodHRwczovL3NlY3VyZXRva2VuLmdvb2dsZS5jb20vbmVlbmQtYXBwIiwiYXVkIjoibmVlbmQtYXBwIiwiYXV0aF90aW1lIjoxNjU1MTE1Njg3LCJ1c2VyX2lkIjoiVWs4ZUVESmk4RE9ndUpyZjZmR00xdkdER1A3MyIsInN1YiI6IlVrOGVFREppOERPZ3VKcmY2ZkdNMXZHREdQNzMiLCJpYXQiOjE2NTUxMTU2ODcsImV4cCI6MTY1NTExOTI4NywiZW1haWwiOiJzdWRtb25kYWwyMDAyQGdtYWlsLmNvbSIsImVtYWlsX3ZlcmlmaWVkIjpmYWxzZSwiZmlyZWJhc2UiOnsiaWRlbnRpdGllcyI6eyJlbWFpbCI6WyJzdWRtb25kYWwyMDAyQGdtYWlsLmNvbSJdfSwic2lnbl9pbl9wcm92aWRlciI6InBhc3N3b3JkIn19.Ba3A--8oLQfRU4-BQO4XEYpaX5AeCoEyY03nf00FeJECuaNP23QwIjFW9xtGsT1gIaqj4P1ZQLCCyJe_z84A6-A1ZTCfNp1cVV--ClftEnTtNIKr7PrcGjKEkJWEKnjThk9vL7lglqcSvRrAAA4c2TGBspXuUyHs7rr8TQvszVvKaw8a13GukMq2jzh-q98jU-aHQQwvBTbiPDmdfMG-g5VsDC1s17GY-DYdLxLG0gEpFcQycagfe6LNFVBMSpOB40mrBZDhomi_weEdDk-VfYwBarvKBAcZTEz-qkRgbrY0-hL1CT2gwBD1whcEBtp8qpPINEaYti4kjgiDHXQfbQ","key":"ID_TOKEN"},{"type":"any","value":"eyJpZCI6MywiZmlyZWJhc2VfdWlkIjoiVWs4ZUVESmk4RE9ndUpyZjZmR00xdkdER1A3MyIsImVtYWlsIjoic3VkbW9uZGFsMjAwMkBnbWFpbC5jb20iLCJuYW1lIjpudWxsLCJwaG9uZSI6bnVsbCwiZmNtX3Rva2VuIjoiMTIzNDU2Nzg5IiwiZ2VuZGVyIjpudWxsLCJpbnRlbnQiOm51bGwsInVwZGF0ZWRfYXQiOiIyMDIyLTA2LTEzVDEwOjI0OjI2Ljc5NVoiLCJjcmVhdGVkX2F0IjoiMjAyMi0wNi0xM1QxMDoyNDoyNi43OTVaIiwiaWF0IjoxNjU1MTE1ODY3LCJleHAiOjE2ODYyMTk4Njd9","key":"USER_TOKEN"},{"type":"any","value":"","key":"AUTH_TOKEN"}],"info":{"_postman_id":"33bbdda5-69df-45a8-bfc6-b2a08f18a8bf","name":"NeendAPI","schema":"https://schema.getpostman.com/json/collection/v2.1.0/collection.json"}}